llmswap/__init__.py
llmswap/__main__.py
llmswap/app.py
llmswap/async_client.py
llmswap/async_providers.py
llmswap/cache.py
llmswap/cli_workspace.py
llmswap/client.py
llmswap/config.py
llmswap/exceptions.py
llmswap/logging_handler.py
llmswap/providers.py
llmswap/py.typed
llmswap/response.py
llmswap/security.py
llmswap/verification.py
llmswap/analytics/__init__.py
llmswap/analytics/price_manager.py
llmswap/analytics/usage_tracker.py
llmswap/cli/__init__.py
llmswap/cli/mcp_cli.py
llmswap/cli/ui.py
llmswap/mcp/__init__.py
llmswap/mcp/circuit_breaker.py
llmswap/mcp/client.py
llmswap/mcp/connection_pool.py
llmswap/mcp/exceptions.py
llmswap/mcp/protocol.py
llmswap/mcp/transports/__init__.py
llmswap/mcp/transports/base.py
llmswap/mcp/transports/http.py
llmswap/mcp/transports/sse.py
llmswap/mcp/transports/stdio.py
llmswap/metrics/__init__.py
llmswap/metrics/cost_estimator.py
llmswap/tools/__init__.py
llmswap/tools/response.py
llmswap/tools/schema.py
llmswap/web/__init__.py
llmswap/web/app.py
llmswap/web/comparison.py
llmswap/web/models.py
llmswap/web/workspace_integration.py
llmswap/web/templates/index.html
llmswap/workspace/__init__.py
llmswap/workspace/detector.py
llmswap/workspace/learnings_tracker.py
llmswap/workspace/manager.py
llmswap/workspace/registry.py
llmswap/workspace/templates.py
llmswap-5.5.4.dist-info/METADATA
llmswap-5.5.4.dist-info/WHEEL
llmswap-5.5.4.dist-info/entry_points.txt
llmswap-5.5.4.dist-info/licenses/LICENSE
llmswap-5.5.4.dist-info/RECORD
