Metadata-Version: 2.4
Name: llmswap
Version: 5.5.4
Summary: Universal LLM SDK + MCP Client: GPT-5.2, Claude Opus 4.5, Gemini 3 Flash, Gemini 3 Pro, Grok 4.1, DeepSeek V3.2 + 10 providers. LMArena top models. Natural language tool calling. Zero vendor lock-in. Production SDK + beautiful CLI.
Project-URL: Homepage, https://github.com/sreenathmmenon/llmswap
Project-URL: Documentation, https://github.com/sreenathmmenon/llmswap#readme
Project-URL: Repository, https://github.com/sreenathmmenon/llmswap
Project-URL: Issues, https://github.com/sreenathmmenon/llmswap/issues
Project-URL: Changelog, https://github.com/sreenathmmenon/llmswap/blob/main/CHANGELOG.md
Author-email: Sreenath M Menon <sreenathmmmenon@gmail.com>
License: MIT License
License-File: LICENSE
Keywords: 10-providers,2025-models,adaptive-learning,age-appropriate-ai,agentic-ai,agents,ai,ai-abstraction-layer,ai-assistant,ai-benchmarks,ai-chat,ai-chat-cli,ai-cli,ai-code-assistant,ai-code-generation,ai-code-review,ai-comparison-tool,ai-context-switching,ai-cost-savings,ai-dashboard,ai-debugging,ai-infrastructure,ai-learning,ai-logs,ai-memory,ai-mentor,ai-pair-programming,ai-persona,ai-personas,ai-provider-switcher,ai-sdk,ai-straying-prevention,ai-teaching,ai-testing-tool,ai-tutor,anthropic
Classifier: Development Status :: 5 - Production/Stable
Classifier: Environment :: Console
Classifier: Framework :: AsyncIO
Classifier: Intended Audience :: Developers
Classifier: Intended Audience :: Education
Classifier: Intended Audience :: Information Technology
Classifier: Intended Audience :: Science/Research
Classifier: License :: OSI Approved :: MIT License
Classifier: Operating System :: OS Independent
Classifier: Programming Language :: Python :: 3
Classifier: Programming Language :: Python :: 3.8
Classifier: Programming Language :: Python :: 3.9
Classifier: Programming Language :: Python :: 3.10
Classifier: Programming Language :: Python :: 3.11
Classifier: Programming Language :: Python :: 3.12
Classifier: Topic :: Communications :: Chat
Classifier: Topic :: Internet :: WWW/HTTP :: Dynamic Content
Classifier: Topic :: Scientific/Engineering :: Artificial Intelligence
Classifier: Topic :: Software Development :: Libraries :: Python Modules
Classifier: Topic :: System :: Distributed Computing
Classifier: Topic :: Text Processing :: Linguistic
Classifier: Typing :: Typed
Requires-Python: >=3.9
Requires-Dist: aiofiles>=23.0.0
Requires-Dist: aiohttp>=3.8.0
Requires-Dist: anthropic>=0.3.0
Requires-Dist: cohere>=5.16.0
Requires-Dist: flask-cors>=4.0.0
Requires-Dist: flask>=3.0.0
Requires-Dist: google-generativeai>=0.3.0
Requires-Dist: groq>=0.4.0
Requires-Dist: httpx>=0.24.0
Requires-Dist: openai>=1.0.0
Requires-Dist: python-dotenv>=0.19.0
Requires-Dist: requests>=2.25.0
Provides-Extra: all
Requires-Dist: anthropic>=0.3.0; extra == 'all'
Requires-Dist: cohere>=5.16.0; extra == 'all'
Requires-Dist: flask-cors>=4.0.0; extra == 'all'
Requires-Dist: flask>=3.0.0; extra == 'all'
Requires-Dist: google-generativeai>=0.3.0; extra == 'all'
Requires-Dist: groq>=0.4.0; extra == 'all'
Requires-Dist: ibm-watsonx-ai>=0.0.5; extra == 'all'
Requires-Dist: openai>=1.0.0; extra == 'all'
Provides-Extra: dev
Requires-Dist: black>=22.0.0; extra == 'dev'
Requires-Dist: isort>=5.10.0; extra == 'dev'
Requires-Dist: mypy>=0.991; extra == 'dev'
Requires-Dist: pytest-cov>=4.0.0; extra == 'dev'
Requires-Dist: pytest>=7.0.0; extra == 'dev'
Provides-Extra: watsonx
Requires-Dist: ibm-watsonx-ai>=0.0.5; extra == 'watsonx'
